[{"data": "2024-09-10", "mgd": "5209.17560", "amount": "100000", "nd": "987010.100924.220241.PHAN THI THUY DUONG chuyen khoan-100924-22:02:39 987010"}, {"data": "2024-09-10", "mgd": "5189.46081", "amount": "1000000", "nd": "020097042209102202402024PQYX930634.4608 1.220241.NGUYEN THI THUY chuyen tien"}, {"data": "2024-09-10", "mgd": "5219.17565", "amount": "1000000", "nd": "782067.100924.220241.DAM LINH HUONG chuyen FT24255659050766"}, {"data": "2024-09-10", "mgd": "5219.16839", "amount": "500000", "nd": "986985.100924.220346.VU HOANG THAI chuyen khoan-100924-22:02:41 986985"}, {"data": "2024-09-10", "mgd": "5387.44862", "amount": "1000000", "nd": "020097040509102202422024NT1Y038312.4486 2.220221.Vietcombank:0011001932418:BUI THI THUONG chuyen tien"}, {"data": "2024-09-10", "mgd": "5387.46089", "amount": "100000", "nd": "020097042209102202412024E1AA615471.4608 9.220242.con con di hoc nen con quyen gop it mai sau con hua con se ung ho nhieu hoen a. Con duoc di hoc co nha o la con rat vui roi hay gui tam tran thanh cua con cho ba con nhe"}, {"data": "2024-09-10", "mgd": "5388.44874", "amount": "500000", "nd": "020097042209102202412024ZVTY385009.4487 4.220242.LE THI NGOC ANH chuyen tien ung ho dong bao lu lut va khac phuc hau qua bao yagi"}, {"data": "2024-09-10", "mgd": "5389.44880", "amount": "2000000", "nd": "020097041509102202422024XP4L712880.44880 .220242.mong moi nguoi binh an"}, {"data": "2024-09-10", "mgd": "5387.46111", "amount": "300000", "nd": "0200970422091022024220245UK6158746.46111 .220243.ung ho bao lu mien bac"}, {"data": "2024-09-10", "mgd": "5017.16867", "amount": "100000", "nd": "564556.100924.220242.IBFT cuu tro mien Bac"}, {"data": "2024-09-10", "mgd": "5189.46121", "amount": "200000", "nd": "020097042209102202432024S4W2784396.4612 1.220235.TRAN QUANG NGOC chuyen khoan"}, {"data": "2024-09-10", "mgd": "5245.66755", "amount": "100000", "nd": "MBVCB.6998389777.NGUYEN THAI SON chuyen tien ung ho thiet hai do con bao so 3 (yagi).CT tu 0611001928963 NGUYEN THAI SON toi 0011001932418 MAT TRAN TO QUOC VN - BAN CUU TRO TW"}, {"data": "2024-09-10", "mgd": "5244.66755", "amount": "50000", "nd": "MBVCB.6998395638.Viet Nam.CT tu 1015775960 LUU THI MY toi 0011001932418 MAT TRAN TO QUOC VN - BAN CUU TRO TW"}, {"data": "2024-09-10", "mgd": "5240.66756", "amount": "200000", "nd": "MBVCB.6998389498.ung ho nguoi dan vung bao lu lut.CT tu 1038832707 NGUYEN THI NGOC ANH toi 0011001932418 MAT TRAN TO QUOC VN - BAN CUU TRO TW"}, {"data": "2024-09-10", "mgd": "5389.44907", "amount": "200000", "nd": "020097042209102202432024ZX6T982046.4490 7.220224.Do Thi Thanh Nguyet UNG HO CHO DONG BAO BI ANH HUONG DO BAO YAGI"}, {"data": "2024-09-10", "mgd": "5189.44911", "amount": "100000", "nd": "020097042209102202432024HTVX327866.4491 1.220244.em xin chia se chut tam long toi ba con vung bao lu"}, {"data": "2024-09-10", "mgd": "5017.16871", "amount": "500000", "nd": "782183.100924.220243.LY TUE BAO LINH chung tay ho tro mien Bac FT24255850108013"}, {"data": "2024-09-10", "mgd": "5219.17600", "amount": "1000000", "nd": "782190.100924.220243.Gia dinh Cu Vid ung ho dong bao vung lu phia Bac FT24255450060043"}, {"data": "2024-09-10", "mgd": "5219.17601", "amount": "500000", "nd": "782197.100924.220243.Ung ho dong bao khac phuc hau qua bao so 3 FT24255486647706"}, {"data": "2024-09-10", "mgd": "5218.16891", "amount": "50000", "nd": "329840.100924.220244.Ung ho dong bao khac phuc con bao so 3 yagi"}, {"data": "2024-09-10", "mgd": "5212.17619", "amount": "50000", "nd": "719784.100924.220240.LE THI NHU HUYEN Chuyen tien"}, {"data": "2024-09-10", "mgd": "5241.66759", "amount": "1000000", "nd": "MBVCB.6998385139.PHAM NGUYEN KIM HANG - Ung ho dong bao bi thiet hai do bao Yagi.CT tu 0071001248663 PHAM NGUYEN KIM HANG toi 0011001932418 MAT TRAN TO QUOC VN - BAN CUU TRO TW"}, {"data": "2024-09-10", "mgd": "5239.66760", "amount": "14587", "nd": "MBVCB.6998390057.NGUYEN THE BAO mong moi nguoi binh an.CT tu 0481000879224 NGUYEN THE BAO toi 0011001932418 MAT TRAN TO QUOC VN - BAN CUU TRO TW"}, {"data": "2024-09-10", "mgd": "5243.66759", "amount": "100000", "nd": "MBVCB.6998390016.PHAM DANG BAO chuyen tien.CT tu 0201000718705 PHAM DANG BAO toi 0011001932418 MAT TRAN TO QUOC VN - BAN CUU TRO TW"}, {"data": "2024-09-10", "mgd": "5390.46153", "amount": "150000", "nd": "020097042209102202442024C6AF854490.4615 3.220225.BUI THU HUONG chuyen tien"}, {"data": "2024-09-10", "mgd": "5389.46159", "amount": "500000", "nd": "020097041509102202452024mlYb713334.46159. 220237.TRINH SUONG NHI Chuyen tien cuutromienBac"}, {"data": "2024-09-10", "mgd": "5213.17648", "amount": "500000", "nd": "782289.100924.220245.NGUYEN KIEU OANH ung ho dong bao bi thiet hai con bao so 3 Yagi FT24255102609274"}, {"data": "2024-09-10", "mgd": "5189.46161", "amount": "500000", "nd": "020097042209102202452024W79B502553.4616 1.220225.Thanh Son Hoang Nhu ung ho dong bao chiu thiet hai vung lu do bao Yagi"}, {"data": "2024-09-10", "mgd": "5389.46163", "amount": "200000", "nd": "020097042209102202452024EG3J635011.46163. 220246.TRUONG THI THU quyen gop khac phuc sau bao yagi"}, {"data": "2024-09-10", "mgd": "5390.46164", "amount": "1000000", "nd": "0200970422091022024520240ZUJ953815.46164 .220246.LE VAN CHIEN chuyen tien"}, {"data": "2024-09-10", "mgd": "5388.46165", "amount": "200000", "nd": "020097042209102202452024VL6A513003.4616 5.220246.ung ho cac tinh thanh bi bao lu"}, {"data": "2024-09-10", "mgd": "5078.99613", "amount": "500000", "nd": "MBVCB.6998395994.NGUYEN HUY QUYET chuyen tien ung ho khac phuc bao.CT tu 0071001323505 NGUYEN HUY QUYET toi 0011001932418 MAT TRAN TO QUOC VN - BAN CUU TRO TW"}, {"data": "2024-09-10", "mgd": "5214.16924", "amount": "200000", "nd": "597531.100924.220246.Ung ho dong bao"}, {"data": "2024-09-10", "mgd": "5213.17661", "amount": "50000", "nd": "782321.100924.220245.BUI HUYNH LONG ck khac phuc bao yagi FT24255503329563"}, {"data": "2024-09-10", "mgd": "5388.44948", "amount": "100000", "nd": "020097042209102202452024ZD88362869.44948 .220226.NGUYEN THI THUY uho dong bao bao lut so 3"}, {"data": "2024-09-10", "mgd": "5242.66766", "amount": "500000", "nd": "MBVCB.6998395986.UNG HO DONG BAO BI LU LUT VA ANH HUONG BAO YAGI.CT tu 9962729908 TRAN THI HONG HOA toi 0011001932418 MAT TRAN TO QUOC VN - BAN CUU TRO TW"}, {"data": "2024-09-10", "mgd": "5215.17671", "amount": "50000", "nd": "565512.100924.220246.IBFT CAO NGUYEN KHANH NAM chuyen tien"}, {"data": "2024-09-10", "mgd": "5219.17677", "amount": "180000", "nd": "782370.100924.220246.Chau gop 1 phan nho khac phuc sau bao so 3 FT24255492630540"}, {"data": "2024-09-10", "mgd": "5017.16942", "amount": "500000", "nd": "782364.100924.220246.PHAM THUY DUNG ung ho dong bao bi lu lut va anh huong cua bao Yagi FT24255258058685"}, {"data": "2024-09-10", "mgd": "5214.16946", "amount": "200000", "nd": "720615.100924.220240.vi con la sinh vien nen con khong co nhieu, hy vong su dong gop nho nhoi nay giup duoc moi nguoi"}, {"data": "2024-09-10", "mgd": "5390.44967", "amount": "200000", "nd": "020097041509102202472024UiHV712962.44967 .220227.LE NGUYEN NHAT ANH chuyen tien ung ho dong bao bi thiet hai do bao Yagi"}, {"data": "2024-09-10", "mgd": "5220.17686", "amount": "200000", "nd": "782402.100924.220247.VO THU HUONG ung ho dong bao FT24255916525729"}, {"data": "2024-09-10", "mgd": "5189.44972", "amount": "100000", "nd": "020097041509102202482024IN5Y712969.44972. 220248.cuu tro"}, {"data": "2024-09-10", "mgd": "5209.16964", "amount": "100000", "nd": "782416.100924.220247.Ung ho dong bao cac tinh, thanh pho thiet hai do bao so 3 FT24255036008648"}, {"data": "2024-09-10", "mgd": "5388.46219", "amount": "700000", "nd": "020097042209102202472024RFSV577132.46219 .220248.MDTS Vong Tien fanpage ung ho chong bao lu Viet Nam co len"}, {"data": "2024-09-10", "mgd": "5388.47001", "amount": "1000000", "nd": "020097042209102202482024F9K5975794.47001 .220249.NGUYEN THI MAI PHUONG chuyen tien ung ho dan qua con bao"}, {"data": "2024-09-10", "mgd": "5209.17721", "amount": "300000", "nd": "564810.100924.220248.IBFT LE HOANG ANH chuyen tien"}, {"data": "2024-09-10", "mgd": "5189.47009", "amount": "200000", "nd": "020097041509102202502024WoTW712990.470 09.220250.Nha Thuoc Hoang Yen"}, {"data": "2024-09-10", "mgd": "5212.17724", "amount": "200000", "nd": "950475.100924.220240.LE THI THUONG CHUYEN KHOAN MAT TRAN TO QUOC VN BAN CUU TRO TW"}, {"data": "2024-09-10", "mgd": "5388.47011", "amount": "500000", "nd": "020097042209102202492024OVIP713379.47011 .220250.2vc HuyThanh quyen gop ung ho ba con lu lut bao yagi"}, {"data": "2024-09-10", "mgd": "5389.46257", "amount": "100000", "nd": "0200970415091022025020249YPU712991.46257 .220229.ung ho mien bac"}, {"data": "2024-09-10", "mgd": "5214.16998", "amount": "100000", "nd": "719939.100924.220246.LE THI THANH HOA Chuyen tien"}, {"data": "2024-09-10", "mgd": "5213.17731", "amount": "200000", "nd": "720645.100924.220241.ung ho dong bao MB"}, {"data": "2024-09-10", "mgd": "5209.16999", "amount": "10000000", "nd": "782510.100924.220249.NGUYEN TRAN PHUONG LAM chuyen FT24255300070001"}, {"data": "2024-09-10", "mgd": "5216.17746", "amount": "500000", "nd": "720744.100924.220245.NGUYEN THI THANH KIEU Chuyen tien ung ho lu lut mien bac"}, {"data": "2024-09-10", "mgd": "5219.17751", "amount": "200000", "nd": "782549.100924.220250.VO NHU QUYNH ung ho dong bao FT24255189060080"}, {"data": "2024-09-10", "mgd": "5218.17765", "amount": "150000", "nd": "782567.100924.220250.TA NHU QUYNH chuyen Ho tro Mien Bac FT24255036008900"}, {"data": "2024-09-10", "mgd": "5218.18031", "amount": "500000", "nd": "782498.100924.220249.TRAN THI NGUYET HA gui ung ho dong bao cac tinh thanh pho bi thiet hai do con bao so 3 gay ra FT24255818561173"}, {"data": "2024-09-10", "mgd": "5240.66782", "amount": "100000", "nd": "MBVCB.6998389371.TRINH THI TRUC QUYNH chuyen tien.CT tu 0481000844523 TRINH THI TRUC QUYNH toi0011001932418 MAT TRAN TO QUOC VN - BAN CUU TRO TW"}, {"data": "2024-09-10", "mgd": "5245.66781", "amount": "500000", "nd": "MBVCB.6998396301.VU DUC NGHIA chuyen tien ung ho khac phuc bao lu.CT tu 0011003964443 VU DUC NGHIA toi 0011001932418 MAT TRAN TO QUOC VN - BAN CUU TRO TW"}, {"data": "2024-09-10", "mgd": "5239.66783", "amount": "100000", "nd": "MBVCB.6998396372.NGUYEN THI ANH NGUYET chuyen tien.CT tu 1016632778 NGUYEN THI ANH NGUYET toi 0011001932418 MAT TRAN TO QUOC VN - BAN CUU TRO TW"}, {"data": "2024-09-10", "mgd": "5212.18038", "amount": "100000", "nd": "208279.100924.220251.DO THI THUY ung ho nguoi dan vung bao"}, {"data": "2024-09-10", "mgd": "5245.66783", "amount": "200000", "nd": "MBVCB.6998390325.yeu to quoc, yeu dong bao.CT tu 0031000337204 NGUYEN THE LAM toi 0011001932418 MAT TRAN TO QUOC VN - BAN CUU TRO TW"}, {"data": "2024-09-10", "mgd": "5387.46292", "amount": "400000", "nd": "0200970415091022025220244eaI713423.46292. 220243.ung ho dong bao chong bao lu"}, {"data": "2024-09-10", "mgd": "5244.66786", "amount": "1000000", "nd": "MBVCB.6998396313.LE NGOC BINH ung ho lu lut.CT tu 0011004376928 LE NGOC BINH toi 0011001932418 MAT TRAN TO QUOC VN - BAN CUU TRO TW"}, {"data": "2024-09-10", "mgd": "5390.47041", "amount": "250000", "nd": "020097042209102202512024TVKH626852.4704 1.220252.mong mng binh an"}, {"data": "2024-09-10", "mgd": "5216.18061", "amount": "200000", "nd": "719988.100924.220248.Tran Thi Phuong Lan ung ho khac phuc Lu Lut"}, {"data": "2024-09-10", "mgd": "5217.18066", "amount": "50000", "nd": "782654.100924.220252.PHAM THI NGOC ANH ung ho dong bao vung lu lut FT24255005137766"}, {"data": "2024-09-10", "mgd": "5214.18069", "amount": "10000", "nd": "665763.100924.220251.LE THI NGOC BICH chuyen tien"}, {"data": "2024-09-10", "mgd": "5078.99649", "amount": "500000", "nd": "MBVCB.6998396104.UH Dong bao khac phuc hau qua thien tai.CT tu 0011004177006 toi 0011001932418 Uy Ban Trung uong Mat tran To quoc Viet Nam"}, {"data": "2024-09-10", "mgd": "5387.46306", "amount": "3000000", "nd": "02009704220910220252202400SE372793.46306. 220253.Xin duoc ung ho ba con bi thiet hai do bao Yagi chuc ba con binh an khoe manh"}, {"data": "2024-09-10", "mgd": "5212.17800", "amount": "100000", "nd": "564683.100924.220252.IBFT DUONG THI KIM YEN chuyen tien"}, {"data": "2024-09-10", "mgd": "5239.66791", "amount": "200000", "nd": "MBVCB.6998396319.PHUNG DOAI HOANG DIEU- Ung ho dong bao bi anh huong bao so 3 YAGY.CT tu 1016808187 PHUNG DOAI HOANG DIEU toi 0011001932418 MAT TRAN TO QUOC VN - BAN CUU TRO TW"}, {"data": "2024-09-10", "mgd": "5213.18078", "amount": "100000", "nd": "468305.100924.220253.ung ho dong bao"}, {"data": "2024-09-10", "mgd": "5390.46322", "amount": "500000", "nd": "020097042209102202522024EEE8220377.46322. 220245.Dang Yen Bao Linh ung ho cuu tro thiet hai bao Yagi"}, {"data": "2024-09-10", "mgd": "5216.17804", "amount": "500000", "nd": "719921.100924.220246.ung ho dong bao trong thien tai lu lut"}, {"data": "2024-09-10", "mgd": "5243.66791", "amount": "400000", "nd": "MBVCB.6998390675.Giang va Ly ung ho dong bao.CT tu 1016923977 NGUYEN THI HUONG LY toi0011001932418 MAT TRAN TO QUOC VN - BAN CUU TRO TW"}, {"data": "2024-09-10", "mgd": "5240.66793", "amount": "500000", "nd": "MBVCB.6998384794.Ung ho ba con bao lu .CT tu 0101001054909 NGUYEN THI PHUONG NHUNG toi 0011001932418 MAT TRAN TO QUOC VN - BAN CUU TRO TW"}, {"data": "2024-09-10", "mgd": "5219.18086", "amount": "300000", "nd": "720845.100924.220249.Ung ho ba con vung bao lu"}, {"data": "2024-09-10", "mgd": "5189.46329", "amount": "200000", "nd": "020097042209102202522024F7NI328887.46329. 220254.Mien Bac co len nhe"}, {"data": "2024-09-10", "mgd": "5244.66793", "amount": "100000", "nd": "MBVCB.6998396365.NGO BA NHAT chuyen tien ung ho Mien Bac.CT tu 0071001067154 NGO BA NHAT toi 0011001932418 MAT TRAN TO QUOC VN - BAN CUU TRO TW"}, {"data": "2024-09-10", "mgd": "5219.18093", "amount": "1000000", "nd": "208314.100924.220254.Cau mong moi nguoi deu binh an"}, {"data": "2024-09-10", "mgd": "5387.46336", "amount": "1000000", "nd": "020097042209102202532024ZU84627025.46336 .220254.chut tam long ung ho bao yagi"}, {"data": "2024-09-10", "mgd": "5209.18099", "amount": "500000", "nd": "597568.100924.220254.ung ho bao yagi"}, {"data": "2024-09-10", "mgd": "5161.11913", "amount": "50000", "nd": "PARTNER.DIRECT_DEBITS_VCB.MSE.6653 7704074.20240910.66537704074-0927775155_U ng ho dong bao dang bi lu lut"}, {"data": "2024-09-10", "mgd": "5161.11875", "amount": "100000", "nd": "PARTNER.DIRECT_DEBITS_VCB.MSE.6653 7705283.20240910.66537705283-0387698296_C on cung dang la sinh vien nen ko co nhieu chi mong gui it tam long"}, {"data": "2024-09-10", "mgd": "5388.46338", "amount": "350000", "nd": "020097042209102202532024A862417937.46338 .220254.TRAN THI HOAI THUONG chuyen tien"}, {"data": "2024-09-10", "mgd": "5189.47071", "amount": "100000", "nd": "0200970405091022025420248UMQ038647.4707 1.220254.Vietcombank:0011001932418:NGUYE N NHAT HUY chuyen tien"}, {"data": "2024-09-10", "mgd": "5161.11928", "amount": "200000", "nd": "PARTNER.DIRECT_DEBITS_VCB.MSE.6653 7313220.20240910.66537313220-0373522079_E m xin gui mot phan nho ho tro mot phan kho khan voi ba con"}, {"data": "2024-09-10", "mgd": "5389.46349", "amount": "50000", "nd": "020097042209102202532024U8U9496481.46349 .220246.mong moi nguoi binh an vuot qua thien tai"}, {"data": "2024-09-10", "mgd": "5220.17824", "amount": "300000", "nd": "721026.100924.220250.NGUYEN CAM TUY Chuyen tien"}, {"data": "2024-09-10", "mgd": "5216.18110", "amount": "100000", "nd": "814410.100924.220245.xin chia se voi dong bao vung bao lu"}, {"data": "2024-09-10", "mgd": "5078.99659", "amount": "100000", "nd": "MBVCB.6998387197.Hoang Mai Huong ung ho khac phuc sau bao Yagi.CT tu 1017875105 HOANG MAI HUONG toi 0011001932418 MAT TRAN TO QUOC VN - BAN CUU TRO TW"}, {"data": "2024-09-10", "mgd": "5189.47076", "amount": "200000", "nd": "020097042209102202542024KMK0334494.4707 6.220255.NGUYEN THI TAM DAN ung ho dong bao mien Bac lu lut Yagi"}, {"data": "2024-09-10", "mgd": "5209.18116", "amount": "200000", "nd": "782776.100924.220254.MAI THI THUY chuyen FT24255740214440"}, {"data": "2024-09-10", "mgd": "5239.66800", "amount": "100000", "nd": "MBVCB.6998390716.NGUYEN THI KIM DUYEN gop chut long thanh bao Yagi.CT tu 0701000406308 NGUYEN THI KIM DUYEN toi 0011001932418 MAT TRAN TO QUOC VN - BAN CUU TRO TW"}, {"data": "2024-09-10", "mgd": "5389.46363", "amount": "500000", "nd": "020097042209102202542024772Y669465.46363. 220256.GD Kiem Them ung ho dong bao bi bao lu Yagi. Moi nguoi hay co gang len nhe. Binh an."}, {"data": "2024-09-10", "mgd": "5216.18141", "amount": "100000", "nd": "208354.100924.220256.mong dong bao mau chong khac phuc duoc hau qua cua bao va binh an"}, {"data": "2024-09-10", "mgd": "5078.99663", "amount": "100000", "nd": "MBVCB.6998396607.TRAN THI THUY DUNG ung ho vung bi anh huong bao Yagi.CT tu 1029166306 TRAN THI THUY DUNG toi 0011001932418 MAT TRAN TO QUOC VN - BAN CUU TRO TW"}, {"data": "2024-09-10", "mgd": "5217.18144", "amount": "1000000", "nd": "782849.100924.220255.NGUYEN THI THUY LINH chia se voi dong bao bi lu lut FT24255136541238"}, {"data": "2024-09-10", "mgd": "5216.18145", "amount": "100000", "nd": "782843.100924.220255.Mong moi nguoi duoc binh an FT24255841045279"}, {"data": "2024-09-10", "mgd": "5219.17856", "amount": "200000", "nd": "719961.100924.220247.BUI NHAT GIANG Chuyen tien ung ho bao lu"}, {"data": "2024-09-10", "mgd": "5189.47097", "amount": "100000", "nd": "0200970422091022025520249DC0791483.47097 .220256.Ho tro dong bao vuot qua bao Yagi"}, {"data": "2024-09-10", "mgd": "5390.46387", "amount": "200000", "nd": "020097042209102202562024GHRK187477.4638 7.220257.ung ho dong bao lu lut cho nguoi dan"}, {"data": "2024-09-10", "mgd": "5242.66805", "amount": "200000", "nd": "MBVCB.6998390753.NGUYEN QUY QUAN chuyen tien.CT tu 1047256946 NGUYEN QUY QUAN toi 0011001932418 MAT TRAN TO QUOC VN - BAN CUU TRO TW"}, {"data": "2024-09-10", "mgd": "5220.17877", "amount": "500000", "nd": "782895.100924.220256.TRAN THI SEN chuyen ung ho ba con vung lu Mien Bac FT24255231091386"}, {"data": "2024-09-10", "mgd": "5390.47114", "amount": "200000", "nd": "0200970415091022025720241nMP713500.4711 4.220237.HO GIA ung ho cac tinh mien bac bi bao lu"}, {"data": "2024-09-10", "mgd": "5217.18182", "amount": "50000", "nd": "782915.100924.220257.Ung ho dong bao FT24255136541400"}, {"data": "2024-09-10", "mgd": "5390.47123", "amount": "50000", "nd": "020097041509102202572024Y2F7713627.47123. 220258.NGUYEN THI PHUONG Chuyen tien ung ho ba con thiet hai do bao yaki"}, {"data": "2024-09-10", "mgd": "5216.18187", "amount": "50000", "nd": "720931.100924.220253.HO THI BICH TRAM Chuyen tien"}, {"data": "2024-09-10", "mgd": "5387.47127", "amount": "100000", "nd": "020097040509102202582024WO52038738.4712 7.220258.Vietcombank:0011001932418:DINH THI THANH HUYEN chuyen tien"}, {"data": "2024-09-10", "mgd": "5218.18189", "amount": "100000", "nd": "782935.100924.220257.Tu Seoul, mong moi nguoi deu duoc binh an. FT24255068282025"}, {"data": "2024-09-10", "mgd": "5189.46407", "amount": "100000", "nd": "020097041509102202582024qKf7713631.46407. 220258.HUYNH THAO NGHI Chuyen tien ung ho khac phuc bao yagi ;cau cho moi nguoi som vuot qua va duocbinh an"}, {"data": "2024-09-10", "mgd": "5242.66811", "amount": "300000", "nd": "MBVCB.6998396828.mot chut tam long gui toi dong bao lu lut.CT tu 0451000474385 NGUYEN MANH QUYNH toi 0011001932418 MAT TRAN TO QUOC VN - BAN CUU TRO TW"}, {"data": "2024-09-10", "mgd": "5240.66811", "amount": "100000", "nd": "MBVCB.6998396431.NGUYEN TIEN KY chuyen tien ung ho dong bao cac tinh anh huong bao so 3 yagi.CT tu 0491000143641 NGUYEN TIEN KY toi 0011001932418 MAT TRAN TO QUOC VN - BAN CUU TRO TW"}, {"data": "2024-09-10", "mgd": "5389.46419", "amount": "3000000", "nd": "020097041509102202582024D1uu713640.46419 .220250.Quyen Gop Chia Se Dot Bao Yagi"}, {"data": "2024-09-10", "mgd": "5078.99677", "amount": "1000000", "nd": "MBVCB.6998383923.PHAM PHUONG ANH ung ho cac tinh mien Bac do bao Yagi.CT tu 0491000023989 PHAM PHUONG ANH toi 0011001932418 MAT TRAN TO QUOC VN - BAN CUU TRO TW"}, {"data": "2024-09-10", "mgd": "5242.66814", "amount": "50000", "nd": "MBVCB.6998391003.DINH THI NGOC HAI .CT tu 1038083775 DINH THI NGOC HAI toi 0011001932418 MAT TRAN TO QUOC VN - BAN CUU TRO TW"}, {"data": "2024-09-10", "mgd": "5388.47158", "amount": "1000000", "nd": "020097042209102202582024IDXA709955.4715 8.220259.Abe 2835 Rise of kingdom . Co len dong bao"}, {"data": "2024-09-10", "mgd": "5189.47160", "amount": "300000", "nd": "020097042209102202582024FG9Y404761.47160 .220259.Thanh Van ung ho dong bao cac tinh thanh pho bi thiet hai"}, {"data": "2024-09-10", "mgd": "5389.47163", "amount": "500000", "nd": "020097041509102202592024P0XN714022.4716 3.220259.Mai Mai cau mong ba con phia Bac se binh an"}, {"data": "2024-09-10", "mgd": "5017.18213", "amount": "500000", "nd": "783006.100924.220258.TRINH BUU CHAU chuyen ung ho cuu tro mien bac FT24255492630430"}, {"data": "2024-09-10", "mgd": "5220.18215", "amount": "500000", "nd": "301246.100924.220258.TRAN THI THANH HUONG UNG HO BA CON VUNG LU"}, {"data": "2024-09-10", "mgd": "5078.99681", "amount": "500000", "nd": "MBVCB.6998389226.LE THI NGOC DAN chuyen tien.CT tu 1036691406 LE THI NGOC DAN toi 0011001932418 MAT TRAN TO QUOC VN - BAN CUU TRO TW"}, {"data": "2024-09-10", "mgd": "5215.18217", "amount": "300000", "nd": "783020.100924.220258.Ung ho khac phuc hau qua bao lu phia bac FT24255659051052"}, {"data": "2024-09-10", "mgd": "5213.18216", "amount": "300000", "nd": "208434.100924.220259.GD PEPPY UNG HO NGUOI DAN VUNG LU LUT"}, {"data": "2024-09-10", "mgd": "5240.66818", "amount": "10000000", "nd": "MBVCB.6998375603.TRANHUESLIMFIT gui chut tam long mong ba con vuot qua bao yagi.CT tu 1019835838 TRAN TAN TAI toi 0011001932418 MAT TRAN TO QUOC VN - BAN CUU TRO TW"}, {"data": "2024-09-10", "mgd": "5217.18234", "amount": "400000", "nd": "783054.100924.220259.LE THI THOAI ung ho lu lut FT24255260829530"}, {"data": "2024-09-10", "mgd": "5215.17932", "amount": "500000", "nd": "208420.100924.220300.ung ho nguoi dan vung bao Yagi"}, {"data": "2024-09-10", "mgd": "5078.99684", "amount": "200000", "nd": "MBVCB.6998396836.BTAI chia se voi cac tinh bi bao lu.CT tu 9932021085 PHAN BA TAI toi 0011001932418 MAT TRAN TO QUOC VN - BAN CUU TRO TW"}, {"data": "2024-09-10", "mgd": "5390.47182", "amount": "2000000", "nd": "020097041509102203002024FEZ6714040.47182 .220300.Ba con mien Bac; co len nha."}, {"data": "2024-09-10", "mgd": "5387.46469", "amount": "100000", "nd": "020097042209102202592024EY4D300744.46469 .220300.DUONG THANH QUY chuyen tien"}, {"data": "2024-09-10", "mgd": "5245.66822", "amount": "100000", "nd": "MBVCB.6998396616.Ung ho dong bao.CT tu 1015163107 TA DUY KHANH toi 0011001932418 MAT TRAN TO QUOC VN - BAN CUU TRO TW"}, {"data": "2024-09-10", "mgd": "5390.46468", "amount": "500000", "nd": "020097040509102203002024Y90W038810.4646 8.220240.Vietcombank:0011001932418:CLB Ho tro Hoc tap DHBK Ha Noi ung ho chia se khac phuc hau qua bao Yagi"}, {"data": "2024-09-10", "mgd": "5017.18247", "amount": "100000", "nd": "783091.100924.220300.Mong tung chut dong gop nho tao thanh suc manh lon ung ho dong bao bi anh huong boi bao FT24255105370450"}, {"data": "2024-09-10", "mgd": "5216.17955", "amount": "50000", "nd": "783113.100924.220300.DAO THI PHUONG LY chuyen FT24255900931489"}, {"data": "2024-09-10", "mgd": "5214.17949", "amount": "500000", "nd": "720953.100924.220254.tam long chia se dong bao dang bi lu lut"}, {"data": "2024-09-10", "mgd": "5161.11880", "amount": "100000", "nd": "PARTNER.DIRECT_DEBITS_VCB.MSE.6653 7706349.20240910.66537706349-0354988672_N GUYEN THI THANH chuyen tien qua MoMo"}, {"data": "2024-09-10", "mgd": "5219.17973", "amount": "10000", "nd": "753661.100924.220301.TRAN VAN TU ung ho dong bao"}, {"data": "2024-09-10", "mgd": "5241.66827", "amount": "3000000", "nd": "MBVCB.6998397100.LAI THI ANH HUYEN chuyen tien.CT tu 0901000150483 LAI THI ANH HUYEN toi 0011001932418 MAT TRAN TO QUOC VN - BAN CUU TRO TW"}, {"data": "2024-09-10", "mgd": "5390.46486", "amount": "100000", "nd": "020097042209102203012024F9MQ127669.4648 6.220302.LE ANH THINH chuyen tien"}, {"data": "2024-09-10", "mgd": "5216.18260", "amount": "500000", "nd": "783144.100924.220301.Ung ho nguoi dan anh huong bao so 3 yagi FT24255953670163"}, {"data": "2024-09-10", "mgd": "5388.46485", "amount": "500000", "nd": "0200970422091022030120248S16835022.46485. 220302.NGUYEN QUANG HOANG MY GIA LAI HO TRO MIEN BAC KHAC PHUC SAU BAO YAGI"}, {"data": "2024-09-10", "mgd": "5390.47205", "amount": "50000", "nd": "020097041509102203022024Zyui714067.47205. 220302.VO DUC TAI chuyen tien"}, {"data": "2024-09-10", "mgd": "5209.18270", "amount": "50000", "nd": "783173.100924.220301.Ung ho dong bao vung bao lu FT24255126276605"}, {"data": "2024-09-10", "mgd": "5390.46492", "amount": "100000", "nd": "020097042209102203012024W28Z179753.4649 2.220302.mot it tam long gui dong bao"}, {"data": "2024-09-10", "mgd": "5388.47214", "amount": "30000", "nd": "0200970422091022030120245T4I264591.47214. 220302.ung ho cac tinh lu lut"}, {"data": "2024-09-10", "mgd": "5189.46495", "amount": "100000", "nd": "020097042209102203012024CLEM373144.4649 5.220254.NGUYEN HAI YEN chuyen tien"}, {"data": "2024-09-10", "mgd": "5240.66830", "amount": "1000000", "nd": "MBVCB.6998395704.Ung ho dong bao mien Bac.CT tu 0781003668888 NGUYEN THU HANG toi 0011001932418 MAT TRAN TO QUOC VN - BAN CUU TRO TW"}, {"data": "2024-09-10", "mgd": "5213.18282", "amount": "100000", "nd": "783200.100924.220302.Ung ho khac phuc bao yagi FT24255272461784"}, {"data": "2024-09-10", "mgd": "5245.66830", "amount": "1000000", "nd": "MBVCB.6998391132.VU THI LOAN chuyen tien ung ho dong bao lu lut.CT tu 0021000252197 VU THI LOAN toi 0011001932418 MAT TRAN TO QUOC VN - BAN CUU TRO TW"}, {"data": "2024-09-10", "mgd": "5216.18288", "amount": "300000", "nd": "722033.100924.220258.NGUYEN THI NGOC LAN Ung ho cuu tro bao so 3 Yagi"}, {"data": "2024-09-10", "mgd": "5389.47220", "amount": "500000", "nd": "0200970422091022030220245BH9784549.47220 .220303.vn"}, {"data": "2024-09-10", "mgd": "5212.18290", "amount": "50000", "nd": "721254.100924.220259.DO THI MINH KHANH Chuyen tien"}, {"data": "2024-09-10", "mgd": "5388.46516", "amount": "20000", "nd": "020097042209102203022024HZM4957133.4651 6.220303.NGUYEN THI HONG NHUNG chia se cung dong bao ca nuoc khac phuc hau qua bao Yagi"}, {"data": "2024-09-10", "mgd": "5209.17999", "amount": "200000", "nd": "565758.100924.220302.IBFT LAM THI HONG NHANG ung ho dong bao mien bac chiu thiet hai cua bao so 3 Yagi"}, {"data": "2024-09-10", "mgd": "5189.47229", "amount": "200000", "nd": "0200970405091022030320243WNV038898.4722 9.220303.Vietcombank:0011001932418:HOAN G THI MAI chuyen tien ung ho dong bao lu lut"}, {"data": "2024-09-10", "mgd": "5240.66835", "amount": "500000", "nd": "MBVCB.6998390673.NGUYEN THI TRANG ung ho ba con vung thien tai .CT tu 1035252941 NGUYEN THI TRANG toi 0011001932418 MAT TRAN TO QUOC VN - BAN CUU TRO TW"}, {"data": "2024-09-10", "mgd": "5215.18300", "amount": "1000000", "nd": "208508.100924.220304.La lanh dum la rach vi mot Viet Nam doan ket vung manh"}, {"data": "2024-09-10", "mgd": "5216.18301", "amount": "3000000", "nd": "783267.100924.220303.Tap the mien nam chia se voi dong bao mien bac lu lut FT24255201316755"}, {"data": "2024-09-10", "mgd": "5388.47238", "amount": "200000", "nd": "020097042209102203032024NA9I103155.47238 .220304.HOANG THI THANH DIEP chuyen tien"}, {"data": "2024-09-10", "mgd": "5390.47239", "amount": "25000", "nd": "0200970422091022030320248N5I217369.47239. 220243.VU PHUONG LINH THAI THUY THAI BINH UNG HO DONG BAO CHONG BAO. CHAU LA HOC SINH NEN KHONG CO NHIEU MONG RANG CO THE GIUP CHUT CHO BA CON VUNG BAO LU GAP KHO KHAN"}, {"data": "2024-09-10", "mgd": "5243.66836", "amount": "1000000", "nd": "MBVCB.6998390821.NGO DUC THIEN chuyen tien.CT tu 0351001120315 NGO DUC THIEN toi 0011001932418 MAT TRAN TO QUOC VN - BAN CUU TRO TW"}, {"data": "2024-09-10", "mgd": "5389.47242", "amount": "200000", "nd": "020097042209102203032024YCO5744994.4724 2.220304.Ung ho dong hao lu lut"}, {"data": "2024-09-10", "mgd": "5387.46535", "amount": "200000", "nd": "020097041509102203042024cyP2713757.46535. 220255.ung ho lu lut mien Bac"}, {"data": "2024-09-10", "mgd": "5245.66838", "amount": "50000", "nd": "MBVCB.6998391013.NGUYEN THI PHUONG UYEN chuyen tien.CT tu 1028012605 NGUYEN THI PHUONG UYEN toi 0011001932418 MAT TRAN TO QUOC VN - BAN CUU TRO TW"}, {"data": "2024-09-10", "mgd": "5390.46546", "amount": "500000", "nd": "0200970422091022030320248E00590542.46546. 220304.Chung tay cung dong bao mien Bac chiu thiet hai sau bao lu"}, {"data": "2024-09-10", "mgd": "5243.66840", "amount": "100000", "nd": "MBVCB.6998397201.HOANG THI NGUYEN ung ho dong bao sau bao yagi.CT tu 1014932097 HOANG THI NGUYEN toi 0011001932418 MAT TRAN TO QUOC VN - BAN CUU TRO TW"}, {"data": "2024-09-10", "mgd": "5216.18318", "amount": "50000", "nd": "783327.100924.220304.NGUYEN MAI LINH chuyen FT24255946902054"}, {"data": "2024-09-10", "mgd": "5078.99706", "amount": "500000", "nd": "MBVCB.6998390616.VUONG HAI NAM transfer.CT tu 0301000430026 VUONG HAI NAM toi0011001932418 MAT TRAN TO QUOC VN - BAN CUU TRO TW"}, {"data": "2024-09-10", "mgd": "5390.46554", "amount": "20000", "nd": "0200970415091022030520244D86714115.46554. 220256.NGUYEN THANH DAT ung ho dong bao bi anh huong bao Yagi"}, {"data": "2024-09-10", "mgd": "5220.18331", "amount": "30000", "nd": "783354.100924.220304.Nguyen Minh Khue chung tay ho tro dong bao trong dot bao so 3 FT24255500766536"}, {"data": "2024-09-10", "mgd": "5390.46557", "amount": "100000", "nd": "020097042209102203042024IQU8812377.46557 .220257.NGO THI TRANG chuyen tien"}, {"data": "2024-09-10", "mgd": "5212.18330", "amount": "200000", "nd": "722058.100924.220259.Chia se voi dong bao bi lu lut"}, {"data": "2024-09-10", "mgd": "5388.47269", "amount": "200000", "nd": "020097042209102203042024OLT3682290.47269 .220305.TRUONG THI THUY AN ung ho khac phuc hau qua bao so 3"}, {"data": "2024-09-10", "mgd": "5161.11986", "amount": "50000", "nd": "PARTNER.DIRECT_DEBITS_VCB.MSE.6653 7117461.20240910.66537117461-0974974195_L E VAN DUONG chuyen tien qua MoMo"}, {"data": "2024-09-10", "mgd": "5388.47273", "amount": "300000", "nd": "020097041509102203052024Xaq6714118.47273 .220245.Bang Tam chuyen tien cuu tro mien Bac"}, {"data": "2024-09-10", "mgd": "5214.19029", "amount": "300000", "nd": "783370.100924.220305.Football association of Thailand generously supports the recovery efforts following Yagi Typhoon effect FT24255090134470"}, {"data": "2024-09-10", "mgd": "5387.46560", "amount": "500000", "nd": "020097042209102203042024ZJCI343399.46560. 220305.NGUYEN THI HUYEN UNG HO DONG BAO BAO LU"}, {"data": "2024-09-10", "mgd": "5218.19033", "amount": "1000000", "nd": "987395.100924.220305.DUONG DAI THANG chuyen khoan-100924-22:03:05 987395"}, {"data": "2024-09-10", "mgd": "5243.66844", "amount": "2000000", "nd": "MBVCB.6998396901.LU NGOC LINH chuyen tien.CT tu 1015117297 LU NGOC LINH toi 0011001932418 MAT TRAN TO QUOC VN - BAN CUU TRO TW"}, {"data": "2024-09-10", "mgd": "5219.18349", "amount": "100000", "nd": "722116.100924.220302.NGUYEN HONG NHUNG mong moi nguoi binh an"}, {"data": "2024-09-10", "mgd": "5217.18354", "amount": "100000", "nd": "783427.100924.220305.Ung ho dong bao bi anh huong do bao so 3 FT24255687030543"}, {"data": "2024-09-10", "mgd": "5388.47289", "amount": "500000", "nd": "020097041509102203062024gwOG713794.4728 9.220306.gd NGUYEN VAN TRONG ung ho bao lu mien bac"}, {"data": "2024-09-10", "mgd": "5220.18360", "amount": "10000", "nd": "475383.100924.220306.LE MINH TAN chuyen tien"}, {"data": "2024-09-10", "mgd": "5078.99718", "amount": "200000", "nd": "MBVCB.6998391459.LE TRAN KHANH LINH ung ho bao so 3 .CT tu 1031838464 LE TRAN KHANH LINH toi 0011001932418 MAT TRAN TO QUOC VN - BAN CUU TRO TW"}, {"data": "2024-09-10", "mgd": "5387.47300", "amount": "200000", "nd": "020097040509102203072024G897038979.47300. 220246.Vietcombank:0011001932418:ung ho dong bao anh huong bao yagi va lu lut mien bac"}, {"data": "2024-09-10", "mgd": "5244.66849", "amount": "3000000", "nd": "MBVCB.6998397273.Nguyen Thi Hang ung ho cuu tro lu lut.CT tu 1024066957 BUI THI THOAI MY toi 0011001932418 MAT TRAN TO QUOC VN - BAN CUU TRO TW"}, {"data": "2024-09-10", "mgd": "5243.66851", "amount": "200000", "nd": "MBVCB.6998384566.NGUYEN NGOC HUY HOANG chuyen tien ung ho.CT tu 1026156030 NGUYEN NGOC HUY HOANG toi 0011001932418 MAT TRAN TO QUOC VN - BAN CUU TRO TW"}, {"data": "2024-09-10", "mgd": "5017.19080", "amount": "200000", "nd": "208592.100924.220307.DOAN THI HONG NGOC chuyen tien"}, {"data": "2024-09-10", "mgd": "5215.19083", "amount": "500000", "nd": "330266.100924.220307.Cuu tro bao yagi"}, {"data": "2024-09-10", "mgd": "5388.46605", "amount": "500000", "nd": "0200970422091022030720243Y9W138227.4660 5.220259.NGUYEN THI TRANG chia se voi dong bao bi lu lut"}, {"data": "2024-09-10", "mgd": "5387.47325", "amount": "500000", "nd": "020097041509102203082024lCxx714158.47325.2 20259.ung ho ba con vung bao lu"}, {"data": "2024-09-10", "mgd": "5388.46616", "amount": "1000000", "nd": "020097042209102203082024HQQ3546891.4661 6.220308.PHAM MINH TAM chuyen tien ung ho dong bao vung lu lut 2024"}, {"data": "2024-09-10", "mgd": "5189.46620", "amount": "50000", "nd": "020097042209102203082024UM18219056.4662 0.220309.VU HOANG UYEN chuyen tien ung ho dong bao mien Bac"}, {"data": "2024-09-10", "mgd": "5389.47339", "amount": "20000", "nd": "020097042209102203082024ZK6F524492.47339 .220309.NGUYEN THI NGOC TRAM HOC SINH TIEN GIANG UNG HO KHAC PHUC BAO YAGI. CHUC TAT CA BINH AN"}, {"data": "2024-09-10", "mgd": "5189.47341", "amount": "100000", "nd": "02009704220910220308202434G2161844.47341. 220309.yagi"}, {"data": "2024-09-10", "mgd": "5212.19099", "amount": "100000", "nd": "783463.100924.220306.NGUYEN NHAT ANH FT24255008384000"}, {"data": "2024-09-10", "mgd": "5017.18429", "amount": "100000", "nd": "783577.100924.220308.HOANG KHANH LINH chuyen FT24255137300980"}, {"data": "2024-09-10", "mgd": "5390.47355", "amount": "100000", "nd": "020097042209102203082024JL73968677.47355. 220309.ung ho mien Bac"}]