[{"data": "2024-09-10", "mgd": "5215.97339", "amount": "340000", "nd": "584516.100924.174408.NGO THI TUNG LINH chuyen tien ung ho dong bao bi anh huong boi bao Yagi - con bao so 3 FT24254892034720"}, {"data": "2024-09-10", "mgd": "5017.96720", "amount": "200000", "nd": "584577.100924.174409.THUY VAN ung ho nguoi dan MB thiet hai do bao Yagi FT24254999035582"}, {"data": "2024-09-10", "mgd": "5214.97383", "amount": "1000000", "nd": "584682.100924.174410.TRAN NGOC BICH chung tay cung dong bao mien bac cau mong moi nguoi binh an FT24254115112528"}, {"data": "2024-09-10", "mgd": "5241.66896", "amount": "50000", "nd": "MBVCB.6995251888.LE VAN QUY con k co nhieu mong gui chut it tam long cho ba con mien bac.CT tu 0461000635051 LE VAN QUY toi 0011001932418 MAT TRAN TO QUOC VN - BAN CUU TRO TW"}, {"data": "2024-09-10", "mgd": "5390.8029", "amount": "500000", "nd": "020097042209101743562024POUR273298.8029. 174411.NGUYEN TRONG TIEN chuyen tien"}, {"data": "2024-09-10", "mgd": "5214.97413", "amount": "100000", "nd": "305781.100924.174411.Ung ho bao Yagi"}, {"data": "2024-09-10", "mgd": "5220.96818", "amount": "1000000", "nd": "596846.100924.174412.Remitly transfer R14307426090"}, {"data": "2024-09-10", "mgd": "5220.97388", "amount": "1000000", "nd": "584708.100924.174410.Ung ho cuu tro sau bao Yagi FT24254810038101"}, {"data": "2024-09-10", "mgd": "5390.8089", "amount": "500000", "nd": "020097042209101743582024DJZE111634.8089. 174405.DANG THI YEN ung ho mien bac than yeu"}, {"data": "2024-09-10", "mgd": "5078.85745", "amount": "100000", "nd": "MBVCB.6995263405.PHAM THI BAY chuyen tien ung ho dong bao lu lut.CT tu 0461000505347 PHAM THI BAY toi 0011001932418 MAT TRAN TO QUOC VN - BAN CUU TRO TW"}, {"data": "2024-09-10", "mgd": "5387.7616", "amount": "3000000", "nd": "020097042209101743592024HE52921708.7616. 174414.NGUYEN THI MAI LAN chuyen tien"}, {"data": "2024-09-10", "mgd": "5220.96930", "amount": "2000000", "nd": "585057.100924.174414.Cuu tro dong bao lu lut FT24254861598414"}, {"data": "2024-09-10", "mgd": "5218.97504", "amount": "500000", "nd": "585163.100924.174415.cau mong binh an cho ca nuoc FT24254210948078"}, {"data": "2024-09-10", "mgd": "5241.66930", "amount": "300000", "nd": "MBVCB.6995263715.DO QUOC NHAT ANH ung ho khac phuc bao so 3 Yagi.CT tu 0301000405369 DO QUOC NHAT ANH toi 0011001932418 MAT TRAN TO QUOC VN - BAN CUU TRO TW"}, {"data": "2024-09-10", "mgd": "5240.66934", "amount": "700000", "nd": "MBVCB.6995263617.Huynh Thanh Sang Dong Bao Mien Nam Ung Ho Bao Lut Mien Bac .CT tu 0321000629285 HUYNH THANH SANG toi 0011001932418 MAT TRAN TO QUOC VN - BAN CUU TRO TW"}, {"data": "2024-09-10", "mgd": "5218.97605", "amount": "200000", "nd": "760499.100924.174407.ung ho dong bao vung lu lut"}, {"data": "2024-09-10", "mgd": "5220.97635", "amount": "50000", "nd": "585229.100924.174415.HO HUYEN TRANG chuyen FT24254271601159"}, {"data": "2024-09-10", "mgd": "5209.98086", "amount": "500000", "nd": "251747.100924.174417.ung ho dong bao lu lut va bi anh huong tu bao Yagi"}, {"data": "2024-09-10", "mgd": "5390.8159", "amount": "1000000", "nd": "020097042209101743592024N71O538771.8159. 174416.Ung ho dong bao cac tinh bao lu"}, {"data": "2024-09-10", "mgd": "5017.97652", "amount": "100000", "nd": "585283.100924.174416.Minh Anh ung ho cac tinh, thanh pho bi thiet hai do bao Yagi FT24254152982708"}, {"data": "2024-09-10", "mgd": "5017.97655", "amount": "50000", "nd": "585445.100924.174417.Beigebird.studio ung ho khac phuc bao Yagi FT24254036243614"}, {"data": "2024-09-10", "mgd": "5244.66950", "amount": "500000", "nd": "MBVCB.6995263113.VU THI LINH TRANG chuyen tien.CT tu 9397075996 VU THI LINH TRANG toi 0011001932418 MAT TRAN TO QUOC VN - BAN CUU TRO TW"}, {"data": "2024-09-10", "mgd": "5390.8288", "amount": "55465", "nd": "020097042209101744042024JEO0596830.8288.1 74400.HA VAN MINH DUC chuyen tien"}, {"data": "2024-09-10", "mgd": "5215.98099", "amount": "1000000", "nd": "585380.100924.174417.LE HOANG TUAN FT24254557071848"}, {"data": "2024-09-10", "mgd": "5218.98157", "amount": "10000", "nd": "394783.100924.174418.Tuong Vi ung ho cuu tro dong bao mien Bac khac phuc hau qua bao Yagi"}, {"data": "2024-09-10", "mgd": "5216.96953", "amount": "100000", "nd": "585069.100924.174414.Viet Nam yeu thuong FT24254223126807"}, {"data": "2024-09-10", "mgd": "5212.98204", "amount": "100000", "nd": "914698.100924.174419.Ho tro dong bao mien Bac chiu anh huong cua bao lu"}, {"data": "2024-09-10", "mgd": "5219.97688", "amount": "200000", "nd": "671712.100924.174419.Ung ho mua bao"}, {"data": "2024-09-10", "mgd": "5220.98217", "amount": "1000000", "nd": "394813.100924.174420.HA THI ANH TUYET chuyen tien Co Len Mien Bac Than Yeu"}, {"data": "2024-09-10", "mgd": "5189.7824", "amount": "1000000", "nd": "020097041509101744202024Mswb861709.7824 .174420.BONG THI HAI chuyen tien ung ho cuu tro ba con vuot qua bao lu"}, {"data": "2024-09-10", "mgd": "5219.98191", "amount": "100000", "nd": "914516.100924.174419.Nguyen Thi Thu Hoai chuyen tien"}, {"data": "2024-09-10", "mgd": "5243.66975", "amount": "200000", "nd": "MBVCB.6995254433.TRAN THI NGHIA chuyen tien ung ho mien bac khac phuc lu lut.CT tu 0651000823356 TRAN THI NGHIA toi 0011001932418 MAT TRAN TO QUOC VN - BAN CUU TRO TW"}, {"data": "2024-09-10", "mgd": "5220.97772", "amount": "500000", "nd": "244685.100924.174421.ung ho dong bao mien Bac vuot qua bao Yagi"}, {"data": "2024-09-10", "mgd": "5161.49794", "amount": "100000", "nd": "PARTNER.DIRECT_DEBITS_VCB.MSE.6651 4911615.20240910.66514911615-0935291104_ Mong moi nguoi binh an"}, {"data": "2024-09-10", "mgd": "5390.8381", "amount": "50000", "nd": "020097042209101744072024ILGN252200.8381. 174423.NGUYEN CHI KIEN"}, {"data": "2024-09-10", "mgd": "5241.66990", "amount": "1000000", "nd": "MBVCB.6995254576.F4 Shop ung ho dong bao cac tinh bi thiet hai do bao so 3.CT tu 9355724702 CHONG NHIT KIN toi 0011001932418 MAT TRAN TO QUOC VN - BAN CUU TRO TW"}, {"data": "2024-09-10", "mgd": "5218.98344", "amount": "1000000", "nd": "759650.100924.174410.NGUYEN THI HUONG Chuyen tien"}, {"data": "2024-09-10", "mgd": "5390.8441", "amount": "161000", "nd": "020097042209101744082024RIH0761040.8441.1 74424.Ung ho dong bao mien Bac vuot qua kho khan"}, {"data": "2024-09-10", "mgd": "5387.9024", "amount": "500000", "nd": "020097042209101744082024V4EZ615703.9024. 174424.TRAN THI THANH HIEN chuyen tien"}, {"data": "2024-09-10", "mgd": "5017.97880", "amount": "100000", "nd": "915721.100924.174423.ho tro khac phuc hau qua bao Yagi"}, {"data": "2024-09-10", "mgd": "5215.98442", "amount": "500000", "nd": "586191.100924.174424.BAN TRONG VIET UNG HO KHAC PHUC BAO LU FT24254136440600"}, {"data": "2024-09-10", "mgd": "5388.8479", "amount": "100000", "nd": "020097042209101744092024YY0L389321.8479. 174426.BUI HUU DIEP chuyen tien"}, {"data": "2024-09-10", "mgd": "5213.98342", "amount": "100000", "nd": "760766.100924.174411.HA MEN Chuyen tien ung ho dong bao mien bac thien tai lu lut"}, {"data": "2024-09-10", "mgd": "5243.67004", "amount": "500000", "nd": "MBVCB.6995264949.Cuu tro dong bao mien Bac bi bao lut.CT tu 0721005086511 HUYNH BAO THACH toi 0011001932418 MAT TRAN TO QUOC VN - BAN CUU TRO TW"}, {"data": "2024-09-10", "mgd": "5218.97886", "amount": "10000000", "nd": "586187.100924.174424.Ung ho cuu tro bao yagi FT24254451385447"}, {"data": "2024-09-10", "mgd": "5217.97690", "amount": "200000", "nd": "759568.100924.174409.cuu tro nan nhan bao yagi"}, {"data": "2024-09-10", "mgd": "5212.97942", "amount": "1000000", "nd": "531186.100924.174425.Ung ho ba con vung lu lut"}, {"data": "2024-09-10", "mgd": "5244.67017", "amount": "5000000", "nd": "MBVCB.6995275176.TONY UNG HO CUU TRO NGUOI DAN VUNG BAO YAGI.CT tu 1113071991 HO LE BAO AN toi 0011001932418 MAT TRAN TO QUOC VN - BAN CUU TRO TW"}, {"data": "2024-09-10", "mgd": "5209.98520", "amount": "200000", "nd": "586322.100924.174426.NGUYEN THU TRANG chuyen chung tay giup dong bao lu FT24254007514061"}, {"data": "2024-09-10", "mgd": "5161.49879", "amount": "500000", "nd": "PARTNER.DIRECT_DEBITS_VCB.MSE.6651 5589460.20240910.66515589460-0833221089_N GUYEN HOANG LAN ANH chuyen tien qua MoMo"}, {"data": "2024-09-10", "mgd": "5078.85873", "amount": "200000", "nd": "MBVCB.6995263709.NGUYEN THI PHUONG LINH chuyen tien so tien it nhung con mong giup duoc nguoi dan o vung lu lut.CT tu 1049696067 NGUYEN THI PHUONG LINH toi 0011001932418 MAT TRAN TO QUOC VN - BAN CUU TRO TW"}, {"data": "2024-09-10", "mgd": "5161.49924", "amount": "100000", "nd": "PARTNER.DIRECT_DEBITS_VCB.MSE.6651 4936361.20240910.66514936361-0938932378_P ham Thanh ung ho dong bao cac tinh bi thiet hai do bao so 3 Yagi"}, {"data": "2024-09-10", "mgd": "5245.67028", "amount": "2000000", "nd": "MBVCB.6995266004.NGUYEN HUYNH TO QUYEN chuyen tien ung dong bao bi anh huong Yagi.CT tu 1016885805 NGUYEN HUYNH TO QUYEN toi 0011001932418 MAT TRAN TO QUOC VN - BAN CUU TRO TW"}, {"data": "2024-09-10", "mgd": "5390.8558", "amount": "100000", "nd": "020097042209101744132024GOA0388845.8558. 174428.LE THI HAI VAN chuyen tien"}, {"data": "2024-09-10", "mgd": "5219.99013", "amount": "100000000", "nd": "915860.100924.174426.LE THI NHI HO TRO KHAC PHUC SAU BAO (by TPBank ChatPay)"}, {"data": "2024-09-10", "mgd": "5389.9196", "amount": "100000", "nd": "0200970422091017441320249R4F347373.9196.1 74429.Nguyen Van Dang ung ho dong bao vung lu mien Bac do bao Yagi"}, {"data": "2024-09-10", "mgd": "5240.67038", "amount": "1000000", "nd": "MBVCB.6995265122.KHUU CANH KIET ung ho khac phuc hau qua bao Yagi.CT tu 0231000611679 KHUU CANH KIET toi 0011001932418 MAT TRAN TO QUOC VN - BAN CUU TRO TW"}, {"data": "2024-09-10", "mgd": "5390.9209", "amount": "100000", "nd": "02009704220910174414202470U4927315.9209.1 74421.NGUYEN VU LINH ung ho bao"}, {"data": "2024-09-10", "mgd": "5214.99028", "amount": "5000000", "nd": "586617.100924.174429.Mong Nguoi dan binh an FT24254256999830"}, {"data": "2024-09-10", "mgd": "5213.99032", "amount": "500000", "nd": "586457.100924.174427.NGUYEN THU HUYEN quyen gop chia se cung dong bao do bao Yagi FT24254345017080"}, {"data": "2024-09-10", "mgd": "5218.99041", "amount": "200000", "nd": "376043.100924.174430.LE HONG TRAM CHUYEN KHOAN"}, {"data": "2024-09-10", "mgd": "5220.98697", "amount": "200000", "nd": "789134.100924.174431.NGUYEN THI AI NHI chuyen tien ung ho cuu tro nguoi dan vung bao"}, {"data": "2024-09-10", "mgd": "5161.49947", "amount": "200000", "nd": "PARTNER.DIRECT_DEBITS_VCB.MSE.6651 5589541.20240910.66515589541-0915226141_C uu tro nguoi dan vung lu"}, {"data": "2024-09-10", "mgd": "5387.8631", "amount": "1000000", "nd": "020097042209101744152024V90D668480.8631. 174431.TRAN THI KIM HOA chuyen tien"}, {"data": "2024-09-10", "mgd": "5161.49935", "amount": "50000", "nd": "PARTNER.DIRECT_DEBITS_VCB.MSE.6651 5589459.20240910.66515589459-0352187616_P HAM THI HONG VAN chuyen tien qua MoMo"}, {"data": "2024-09-10", "mgd": "5217.98734", "amount": "3000000", "nd": "586799.100924.174430.Mai Suong ck ung ho dong bao Mien bac FT24254070034410"}, {"data": "2024-09-10", "mgd": "5216.99116", "amount": "200000", "nd": "759848.100924.174415.HO MANH CUONG ung ho nguoi dan thiet hai bao lu"}, {"data": "2024-09-10", "mgd": "5215.99110", "amount": "100000", "nd": "931754.100924.174432.Dao Le Nyk gui ho tro dong bao bi lu lut"}, {"data": "2024-09-10", "mgd": "5387.8400", "amount": "134000", "nd": "020097042209101744072024QGDJ201691.8400. 174423.NGUYEN MINH CHIEN chuyen tien"}, {"data": "2024-09-10", "mgd": "5245.67058", "amount": "100000", "nd": "MBVCB.6995265240.Ung ho.CT tu 0031000294043 DANG HA ANH toi 0011001932418 MAT TRAN TO QUOC VN - BAN CUU TRO TW"}, {"data": "2024-09-10", "mgd": "5189.9310", "amount": "100000", "nd": "020097042209101744152024CFUJ747621.9310. 174433.Mong mn binh an va vuot qua thien tai"}, {"data": "2024-09-10", "mgd": "5218.99078", "amount": "200000", "nd": "586589.100924.174428.TRAN THI HA Ho tro dong bao FT24254510023438"}, {"data": "2024-09-10", "mgd": "5078.85924", "amount": "1000000", "nd": "MBVCB.6995254705.Xin ung bo ba con khac phuc thien tai.CT tu 0071001133917 LE THI NHU toi0011001932418 MAT TRAN TO QUOC VN - BAN CUU TRO TW"}, {"data": "2024-09-10", "mgd": "5189.8708", "amount": "200000", "nd": "020097040509101744332024O11R035162.8708. 174433.Vietcombank:0011001932418:UNG HO DONG BAO DO CON BAO YAGI"}, {"data": "2024-09-10", "mgd": "5390.8711", "amount": "200000", "nd": "020097040509101744332024X83O035154.8711. 174413.Vietcombank:0011001932418:DANG THI HOAI THUONG UNG HO BA CON VUNG BAO LU"}, {"data": "2024-09-10", "mgd": "5213.99148", "amount": "1000000", "nd": "915379.100924.174432.Chia se cung ba con mien Bac khac phuc hau qua bao lu"}, {"data": "2024-09-10", "mgd": "5189.8736", "amount": "300000", "nd": "020097041509101744342024rVH6862669.8736.1 74426.PHAM GIA DUC chuyen tien ung ho dong bao"}, {"data": "2024-09-10", "mgd": "5219.98812", "amount": "500000", "nd": "586912.100924.174432.Cong dong SBTC - TTHL ung ho dong bao lu lut. FT24254572161927"}, {"data": "2024-09-10", "mgd": "5216.99168", "amount": "500000", "nd": "931778.100924.174433.Gia dinh chau Bao Huy ho tro dong bao mien Bac"}, {"data": "2024-09-10", "mgd": "5189.8741", "amount": "30000", "nd": "020097042209101744192024QJYM281826.8741 .174434.Chon nho cua Dong Vu Khon ung ho cac vung bao lu"}, {"data": "2024-09-10", "mgd": "5220.98836", "amount": "1000000", "nd": "587000.100924.174433.Ung ho dong bao lu lut - Chung tay vuot qua con bao FT24254022086570"}, {"data": "2024-09-10", "mgd": "5212.98840", "amount": "300000", "nd": "762197.100924.174422.unghobaoyagi"}, {"data": "2024-09-10", "mgd": "5387.8760", "amount": "100000", "nd": "020097040509101744352024CJCO035291.8760. 174435.Vietcombank:0011001932418:BUI THI KIM THUC chuyen tien UHDB bao so 3"}, {"data": "2024-09-10", "mgd": "5078.85943", "amount": "200000", "nd": "MBVCB.6995265987.Phu Phuc sport thuong chuc mien Bac som vuot qua kho khan.CT tu 0121000804653 NGUYEN DINH TO UYEN toi 0011001932418 MAT TRAN TO QUOC VN - BAN CUU TRO TW"}, {"data": "2024-09-10", "mgd": "5389.9435", "amount": "5000000", "nd": "0200970405091017443520242V14035321.9435.1 74436.UNG HO CUU TRO BAO LUT MIEN BAC VN"}, {"data": "2024-09-10", "mgd": "5390.8804", "amount": "150000", "nd": "020097042209101744192024N5VK198990.8804. 174436.gia dinh Loc Teo ung ho ba con lu lut"}, {"data": "2024-09-10", "mgd": "5217.98931", "amount": "1000000", "nd": "915525.100924.174434.Ung ho dong bao chong lu"}, {"data": "2024-09-10", "mgd": "5213.98942", "amount": "2000", "nd": "742013.100924.174434.LEO TRUNG HIEU cua it nhung long nhieu mong giup do duoc phan nao a"}, {"data": "2024-09-10", "mgd": "5220.99275", "amount": "20000", "nd": "789295.100924.174435.le ngoc hung ung ho khac phuc bao yagi"}, {"data": "2024-09-10", "mgd": "5216.99277", "amount": "100000", "nd": "931816.100924.174434.NGUYEN THI DIEU LINH chuyen tien den MAT TRAN TO QUOC VN - BAN CUU TRO TW - 0011001932418"}, {"data": "2024-09-10", "mgd": "5218.99346", "amount": "500000", "nd": "789355.100924.174437.ung ho dong bao bi anh huong boi bao so 3"}, {"data": "2024-09-10", "mgd": "5209.99385", "amount": "1000000", "nd": "789386.100924.174438.NGUYEN THI PHUONG THANH chuyen tien cuu tro dong bao lu lut"}, {"data": "2024-09-10", "mgd": "5212.78", "amount": "500000", "nd": "607458.100924.174436.LE THUY HIEN TRANSFER MONG GIUP DC GI DO CHO DONG BAO-100924-17:44:37 607458"}, {"data": "2024-09-10", "mgd": "5387.9535", "amount": "1000000", "nd": "020097042209101744222024MZ24273054.9535. 174439.DINH THI TRANG LINH chuyen tien"}, {"data": "2024-09-10", "mgd": "5215.102", "amount": "50000", "nd": "789396.100924.174438.Ung ho cac tinh bao lu"}, {"data": "2024-09-10", "mgd": "5212.99424", "amount": "500000", "nd": "587556.100924.174438.TRUONG THI THU HANG ung ho dong bao cac tinh bi thiet hai do bao so 3 yagi FT24254529923927"}, {"data": "2024-09-10", "mgd": "5219.99439", "amount": "200000", "nd": "587436.100924.174437.Chung tay ho tro dong bao chiu anh huong thien tai FT24254208871963"}, {"data": "2024-09-10", "mgd": "5240.67127", "amount": "500000", "nd": "MBVCB.6995267070.NGUYEN THI NHU NGOC chuyen tien ung ho khac phuc bao Yagi.CT tu 1036047032 NGUYEN THI NHU NGOC toi 0011001932418 MAT TRAN TO QUOC VN - BAN CUU TRO TW"}, {"data": "2024-09-10", "mgd": "5216.183", "amount": "2000000", "nd": "587676.100924.174439.Ung Ho Dong Bao Phia Bac Khac Phuc Bao Yagi FT24254700127899"}, {"data": "2024-09-10", "mgd": "5217.188", "amount": "50000", "nd": "587466.100924.174437.ung ho dong bao FT24254195155075"}, {"data": "2024-09-10", "mgd": "5189.8968", "amount": "500000", "nd": "020097042209101744252024IVG4319669.8968.1 74433.FB Linh Xinh ung ho dong bao lu lut"}, {"data": "2024-09-10", "mgd": "5239.67136", "amount": "1000000", "nd": "MBVCB.6995267014.NGUYEN THI HUONG chuyen tien ung ho dong bao vung lu.CT tu 0021000464625 NGUYEN THI HUONG toi 0011001932418 MAT TRAN TO QUOC VN - BAN CUU TRO TW"}, {"data": "2024-09-10", "mgd": "5213.246", "amount": "200000", "nd": "916850.100924.174440.Ung ho khac phuc bao lu dong bao mien bac"}, {"data": "2024-09-10", "mgd": "5220.264", "amount": "500000", "nd": "587960.100924.174441.Ung ho dong bao gap nan trong bao lu a FT24254274474047"}, {"data": "2024-09-10", "mgd": "5017.242", "amount": "100000", "nd": "762151.100924.174421.PHAN THI THANH HANG Ung ho khac phuc sau bao so 3 Yagi"}, {"data": "2024-09-10", "mgd": "5214.99533", "amount": "200000", "nd": "932062.100924.174443.Ung ho khac phuc thiet hai bao so 3"}, {"data": "2024-09-10", "mgd": "5214.270", "amount": "100000", "nd": "509232.100924.174440.NTNA UNG HO DONG BAO LU LUT"}, {"data": "2024-09-10", "mgd": "5242.67145", "amount": "200000", "nd": "MBVCB.6995267651.ung ho dong bao lu lut.CT tu 0091000683416 CHAU QUOI THI toi 0011001932418 MAT TRAN TO QUOC VN - BAN CUU TRO TW"}, {"data": "2024-09-10", "mgd": "5216.299", "amount": "100000", "nd": "763246.100924.174436.NGUYEN THI NGOC MAI CHUYEN TIEN UNG HO THIET HAI BAO YAGI"}, {"data": "2024-09-10", "mgd": "5078.86010", "amount": "2000000", "nd": "MBVCB.6995252402.TRINH THI HOA chuyen tien.CT tu 0011004214165 TRINH THI HOA toi 0011001932418 MAT TRAN TO QUOC VN - BAN CUU TRO TW"}, {"data": "2024-09-10", "mgd": "5216.321", "amount": "200000", "nd": "422165.100924.174442.ung ho khac phuc bao lu"}, {"data": "2024-09-10", "mgd": "5218.99586", "amount": "200000", "nd": "587970.100924.174442.Thu Nhi ung ho khac phuc hau qua bao yagi FT24254717984092"}, {"data": "2024-09-10", "mgd": "5212.335", "amount": "100000", "nd": "932109.100924.174444.le thi diem chuyen tien ung ho dong bao bi thiet hai do thien tai"}, {"data": "2024-09-10", "mgd": "5217.99615", "amount": "10000", "nd": "762043.100924.174419.DANG MY NHAT Chuyen tien"}, {"data": "2024-09-10", "mgd": "5078.86018", "amount": "100000", "nd": "MBVCB.6995266386.Mong moi nguoi vuot qua con bao yagi a.CT tu 1021029375 TRUONG THI PHUONG THAO toi 0011001932418 MAT TRAN TO QUOC VN - BAN CUU TRO TW"}, {"data": "2024-09-10", "mgd": "5220.99610", "amount": "1000000", "nd": "422089.100924.174444.Cuu tro bao Yagi"}, {"data": "2024-09-10", "mgd": "5078.86016", "amount": "10000", "nd": "MBVCB.6995267499.Ho tro thiet hai bao Yagi.CT tu 1040463145 NGUYEN VO AI MI toi 0011001932418 MAT TRAN TO QUOC VN - BAN CUU TRO TW"}, {"data": "2024-09-10", "mgd": "5209.392", "amount": "1000000", "nd": "917787.100924.174443.Trinh Gia Bao ung ho dong bao vung lu lut"}, {"data": "2024-09-10", "mgd": "5218.99664", "amount": "1000000", "nd": "762977.100924.174436.NGUYEN BA LOC gop chut tam long ung ho ba con vung bao lu"}, {"data": "2024-09-10", "mgd": "5219.99675", "amount": "200000", "nd": "917865.100924.174445.Vu Hong Linh ung ho dong bao"}, {"data": "2024-09-10", "mgd": "5219.99689", "amount": "1000000", "nd": "588346.100924.174445.Ung ho dong bao lu lut lao cai yen bai thai nguyen bi anh huong boi bao Yagi FT24254365499865"}, {"data": "2024-09-10", "mgd": "5209.397", "amount": "100000", "nd": "588263.100924.174444.NGUYEN THI SON chuyen FT24254375180029"}, {"data": "2024-09-10", "mgd": "5390.10132", "amount": "100000", "nd": "0200970422091017443020246VEF966734.10132 .174447.Quyen Gop Cho Dong Bao Gap Bao Lu"}, {"data": "2024-09-10", "mgd": "5217.99716", "amount": "300000", "nd": "917926.100924.174446.Panda ung ho dong bao khac phuc bao Yagi"}, {"data": "2024-09-10", "mgd": "5218.99724", "amount": "100000", "nd": "763425.100924.174439.ung ho cac tinh bi bao lu"}, {"data": "2024-09-10", "mgd": "5078.86037", "amount": "100000", "nd": "MBVCB.6995267986.noi vong tay lon. ho tro mien bac.CT tu 1027424109 HUYNH DINH DIEU NGOAN toi 0011001932418 MAT TRAN TO QUOC VN - BAN CUU TRO TW"}, {"data": "2024-09-10", "mgd": "5215.99764", "amount": "2000000", "nd": "588530.100924.174447.Ung ho mien Bac vuot qua bao Yagi FT24254280756633"}, {"data": "2024-09-10", "mgd": "5212.516", "amount": "200000", "nd": "918003.100924.174447.Huynh Truc Linh chuyen tien ung ho dong bao thiet hai do bao so 3"}, {"data": "2024-09-10", "mgd": "5017.99775", "amount": "100000", "nd": "588610.100924.174448.NGUYEN THI BICH NGOC FT24254754430999"}, {"data": "2024-09-10", "mgd": "5217.530", "amount": "3000000", "nd": "588609.100924.174448.Thuy Duong ung ho khac phuc hau qua bao Yagi, cau mong mn binh an FT24254900145480"}, {"data": "2024-09-10", "mgd": "5161.50076", "amount": "100000", "nd": "PARTNER.DIRECT_DEBITS_VCB.MSE.6651 5592460.20240910.66515592460-0964721055_N GUYEN NHAT HOANG chuyen tien qua MoMo"}, {"data": "2024-09-10", "mgd": "5189.10187", "amount": "200000", "nd": "020097041509101744492024QXAv863480.1018 7.174449.PHUNG PHUONG NGA chuyen tien ho tro dong bao bi thiet hai do bao lu"}, {"data": "2024-09-10", "mgd": "5242.67195", "amount": "100000", "nd": "MBVCB.6995276953.DINH THI ANH NGOC chuyen tien.CT tu 1038131194 DINH THI ANH NGOC toi 0011001932418 MAT TRAN TO QUOC VN - BAN CUU TRO TW"}, {"data": "2024-09-10", "mgd": "5390.9921", "amount": "100000", "nd": "020097042209101744342024DF1V931958.9921. 174450.TA HOANG THAO ung ho dong bao cac tinh bi thiet hai sau bao"}, {"data": "2024-09-10", "mgd": "5387.10218", "amount": "500000", "nd": "020097042209101744342024XJHG683216.1021 8.174450.TRAN THI THUY chuyen tien"}, {"data": "2024-09-10", "mgd": "5239.67204", "amount": "378370", "nd": "MBVCB.6995267809.iceh sends with love.CT tu 1029176282 NGUYEN TRAN CONG HUY toi 0011001932418 MAT TRAN TO QUOC VN - BAN CUU TRO TW"}, {"data": "2024-09-10", "mgd": "5239.67207", "amount": "50000", "nd": "MBVCB.6995268464.VO THI THANH NHAN co len mng.CT tu 1024128534 VO THI THANH NHAN toi 0011001932418 MAT TRAN TO QUOC VN - BAN CUU TRO TW"}, {"data": "2024-09-10", "mgd": "5387.10282", "amount": "100000", "nd": "020097041509101744522024GYbO863711.1028 2.174452.ung ho dong bao mien bac"}, {"data": "2024-09-10", "mgd": "5388.10267", "amount": "100000", "nd": "020097041509101744522024Wv0p864083.1026 7.174431.DO VAN CHUC ung ho dong bao lu lut"}, {"data": "2024-09-10", "mgd": "5217.580", "amount": "500000", "nd": "763555.100924.174442.Ung ho dong bao chong thien tai"}, {"data": "2024-09-10", "mgd": "5219.584", "amount": "200000", "nd": "789879.100924.174450.NGUYEN TRI DUNG chuyen tien ung ho dong bao"}, {"data": "2024-09-10", "mgd": "5242.67223", "amount": "300000", "nd": "MBVCB.6995266346.Ung ho khac phuc bao lu Yagi.CT tu 0181003512040 VU NGOC MAI toi 0011001932418 MAT TRAN TO QUOC VN - BAN CUU TRO TW"}, {"data": "2024-09-10", "mgd": "5189.10320", "amount": "63000", "nd": "020097042209101744372024V5UX708318.1032 0.174453.TRAN LE THIEN PHU chuyen tien"}, {"data": "2024-09-10", "mgd": "5241.67228", "amount": "100000", "nd": "MBVCB.6995267759.DO THI NGOC LINH sv nam 2 truong HIEC ung ho khac phuc bao Yagi.CT tu 1032792637 DO THI NGOC LINH toi 0011001932418 MAT TRAN TO QUOC VN - BAN CUU TRO TW"}, {"data": "2024-09-10", "mgd": "5390.11057", "amount": "100000", "nd": "020097040509101744532024XL5V036549.11057 .174453.Vietcombank:0011001932418:ung ho dong bao"}, {"data": "2024-09-10", "mgd": "5244.67230", "amount": "300000", "nd": "MBVCB.6995268578.em xin dong gop chut it mong ba con mien bac luon an toan va manh khoe,.CT tu 1049606814 TRAN TRUONG MINH PHUC toi 0011001932418 MAT TRAN TO QUOC VN - BAN CUU TRO TW"}, {"data": "2024-09-10", "mgd": "5209.631", "amount": "100000", "nd": "789917.100924.174452.TONG DUY TAN chuyen tien ung ho dong bao sau bao Yagi"}, {"data": "2024-09-10", "mgd": "5218.582", "amount": "200000", "nd": "607813.100924.174450.PHAN THI HA AN chuyen khoan-100924-17:44:50 607813"}, {"data": "2024-09-10", "mgd": "5387.11092", "amount": "50000", "nd": "020097042209101744382024O7HL542876.1109 2.174454.gia uyen ung ho mng o vung bi anh huong boi bao so 3 a. chau cua it long nhieu chau xin cam on moi nguoi. mong moi nguoi se gui nhung mon qua den nguoi dan a"}, {"data": "2024-09-10", "mgd": "5388.11102", "amount": "200000", "nd": "020097041509101744542024mZzY863786.11102 .174454.ung ho dong bao khac phuc hau qua do con bao"}, {"data": "2024-09-10", "mgd": "5218.99911", "amount": "29048", "nd": "607902.100924.174602.HUYNH LE TUAN KIET chuyen khoan-100924-17:44:52 607902"}, {"data": "2024-09-10", "mgd": "5239.67233", "amount": "1000000", "nd": "MBVCB.6995268798.UNG HO DONG BAO VUOT QUA BAO YAGI.CT tu 0611001938144 NGUYEN HONG ANH toi 0011001932418 MAT TRAN TO QUOC VN - BAN CUU TRO TW"}, {"data": "2024-09-10", "mgd": "5216.99955", "amount": "500000", "nd": "764294.100924.174442.Ung ho cac tinh thiet hai do bao so 3 va lu lut"}, {"data": "2024-09-10", "mgd": "5214.623", "amount": "2000000", "nd": "588874.100924.174450.TRAN THI PHUONG THAO chuyen FT24254308865294"}, {"data": "2024-09-10", "mgd": "5216.99967", "amount": "1000000", "nd": "760941.100924.174414.Gia dinh Tho ung ho dong bao vung lu lut"}, {"data": "2024-09-10", "mgd": "5390.9981", "amount": "20000", "nd": "020097042209101744362024TAWK435333.998 1.174431.DO THI KIM NGAN chuyen tien"}, {"data": "2024-09-10", "mgd": "5214.1033", "amount": "10000", "nd": "310154.100924.174451.NGUYEN NGOC TU chuyen tien"}, {"data": "2024-09-10", "mgd": "5161.50146", "amount": "15000", "nd": "PARTNER.DIRECT_DEBITS_VCB.MSE.6651 5592646.20240910.66515592646-0796627915_U ng ho dong bao mien Bac"}, {"data": "2024-09-10", "mgd": "5390.11154", "amount": "1000000", "nd": "020097041509101744562024PJzW864208.11154 .174456.UNG HO DONG BAO CAC TINH TP BI THIET HAI DO BAO YAGI"}, {"data": "2024-09-10", "mgd": "5244.67250", "amount": "500000", "nd": "MBVCB.6995267097.DINH THI THU HA chuyen tien ung ho dong bao bi anh huong bao Yagi.CT tu 0051000155640 DINH THI THU HA toi 0011001932418 MAT TRAN TO QUOC VN - BAN CUU TRO TW"}, {"data": "2024-09-10", "mgd": "5389.11223", "amount": "1000000", "nd": "020097042209101744382024LXRQ685585.1122 3.174458.Thuy Nguyen Ung Ho Dong Bao Cac Tinh Bi Thiet Hai Do Bao Lu"}, {"data": "2024-09-10", "mgd": "5218.1049", "amount": "1000000", "nd": "789969.100924.174453.LUONG THI CAM VAN chuyen tien UH ba con vung lu T092024"}, {"data": "2024-09-10", "mgd": "5239.67263", "amount": "200000", "nd": "MBVCB.6995267514.cuu tro thiet hai do bao yagi.CT tu 0531002579616 NGUYEN THI NGOC THUY toi 0011001932418 MAT TRAN TO QUOC VN - BAN CUU TRO TW"}, {"data": "2024-09-10", "mgd": "5215.877", "amount": "10000", "nd": "310644.100924.174455.NGUYEN PHUONG THAO uho cong tac khac phuc phong chong lu lut"}, {"data": "2024-09-10", "mgd": "5017.880", "amount": "4828", "nd": "163930.100924.174457.chau sinh vien ko dk co chut tam long thoi a"}, {"data": "2024-09-10", "mgd": "5213.1140", "amount": "200000", "nd": "918507.100924.174457.Ung ho nguoi dan bi lu lut va bao yagi"}, {"data": "2024-09-10", "mgd": "5389.10488", "amount": "200000", "nd": "020097041509101744592024Z9L1863925.10488. 174459.ung ho cac tinh lu lut mien bac"}, {"data": "2024-09-10", "mgd": "5219.921", "amount": "1000000", "nd": "589516.100924.174457.DAO THI HA ung ho cuu tro nguoi dan gap thien tai FT24254732605807"}, {"data": "2024-09-10", "mgd": "5189.10520", "amount": "100000", "nd": "020097042209101744442024A8E5985942.10520 .174459.DOAN NGOC MY chuyen tien"}, {"data": "2024-09-10", "mgd": "5017.950", "amount": "200000", "nd": "589485.100924.174456.Ung ho dong bao khac phuc hau qua con bao so 3 FT24254087864470"}, {"data": "2024-09-10", "mgd": "5243.67279", "amount": "200000", "nd": "MBVCB.6995265301.CS Mai Anh ung ho lu lut mien Bac .CT tu 0201000728494 LE MAI ANH toi 0011001932418 MAT TRAN TO QUOC VN - BAN CUU TRO TW"}, {"data": "2024-09-10", "mgd": "5388.10544", "amount": "100000", "nd": "020097042209101744432024YN5Q878658.1054 4.174500.ung ho dong bao mien Bac"}, {"data": "2024-09-10", "mgd": "5217.802", "amount": "1000000", "nd": "589183.100924.174453.Ngoc An ung ho dong bao anh huong bao Yagi FT24254804471326"}, {"data": "2024-09-10", "mgd": "5389.10536", "amount": "1000000", "nd": "020097042209101744442024R24B437664.10536 .174440.Ung ho mot chut tam long den Mien Bac"}, {"data": "2024-09-10", "mgd": "5189.10582", "amount": "200000", "nd": "020097042209101744452024TCMN508758.105 82.174441.HAN THI HONG HIEU ung ho bao lut"}, {"data": "2024-09-10", "mgd": "5388.10580", "amount": "300000", "nd": "02009704050910174501202468CV037104.10580 .174501.Vietcombank:0011001932418:LE MONG TRINH chuyen tien ung ho ba con vung lu"}, {"data": "2024-09-10", "mgd": "5240.67295", "amount": "100000", "nd": "MBVCB.6995279722.ung ho dong bao gap thien tai.CT tu 1040770846 BUI THI THANH TAM toi 0011001932418 MAT TRAN TO QUOC VN - BAN CUU TRO TW"}, {"data": "2024-09-10", "mgd": "5220.2048", "amount": "200000", "nd": "765295.100924.174455.TRAN VUONG NGOC PHUC Chuyen tien"}, {"data": "2024-09-10", "mgd": "5388.11358", "amount": "500000", "nd": "020097041509101745022024yptC864392.11358. 174502.LUONG VIET THIEN ung ho dong bao cac tinh thiet hai do bao yagi gay ra"}, {"data": "2024-09-10", "mgd": "5209.2096", "amount": "200000", "nd": "764931.100924.174454.mien bac co len"}, {"data": "2024-09-10", "mgd": "5215.2086", "amount": "500000", "nd": "918813.100924.174457.Nguyen Quoc Viet ung ho cac tinh bao lu"}, {"data": "2024-09-10", "mgd": "5212.2099", "amount": "52000", "nd": "590079.100924.174502.TRAN MINH PHUOC chuyen tien FT24254876290482"}, {"data": "2024-09-10", "mgd": "5239.67312", "amount": "200000", "nd": "MBVCB.6995269394.UNG HO BAO LU.CT tu 0351001020235 NGUYEN THI TUYEN toi 0011001932418 MAT TRAN TO QUOC VN - BAN CUU TRO TW"}, {"data": "2024-09-10", "mgd": "5219.1297", "amount": "100000", "nd": "763813.100924.174446.NGUYEN THI THUY VAN Chuyen tien"}, {"data": "2024-09-10", "mgd": "5161.50203", "amount": "200000", "nd": "PARTNER.DIRECT_DEBITS_VCB.MSE.6651 5594789.20240910.66515594789-0906790845_u ng ho dong bao bi thiet hai do bao"}, {"data": "2024-09-10", "mgd": "5387.11493", "amount": "100000", "nd": "020097041509101745052024RgKK864492.1149 3.174505.ung ho dong bao lu lut."}, {"data": "2024-09-10", "mgd": "5389.11441", "amount": "100000", "nd": "020097042209101744472024617C311336.11441. 174504.DAU DINH DUC ung ho cuu tro"}, {"data": "2024-09-10", "mgd": "5387.11510", "amount": "100000", "nd": "020097042209101744492024RDRB253092.1151 0.174505.TRUONG THI DUNG NHI chuyen tien"}, {"data": "2024-09-10", "mgd": "5189.11520", "amount": "200000", "nd": "020097042209101744472024TQ9P282588.11520 .174505.TRAN HUONG THAO chuyen tien"}, {"data": "2024-09-10", "mgd": "5239.67325", "amount": "25000", "nd": "MBVCB.6995269698.Tran Thanh Tung ung ho ba con chiu anh huong bao lu.CT tu 9779925656 TRAN THANH TUNG toi 0011001932418 MAT TRAN TO QUOC VN - BAN CUU TRO TW"}, {"data": "2024-09-10", "mgd": "5220.1467", "amount": "300000", "nd": "590205.100924.174504.Tan Hung ung ho dong bao chong bao yagi FT24254764425435"}, {"data": "2024-09-10", "mgd": "5219.1508", "amount": "1000000", "nd": "590396.100924.174506.Ung ho nguoi dan vung lu lut FT24254275434006"}, {"data": "2024-09-10", "mgd": "5220.2274", "amount": "30000000", "nd": "763810.100924.174446.Ung ho dong bao lu lut mien Bac"}, {"data": "2024-09-10", "mgd": "5209.2271", "amount": "20000", "nd": "790457.100924.174507.DANG THU ANH quyen gop"}, {"data": "2024-09-10", "mgd": "5387.11616", "amount": "500000", "nd": "020097042209101744532024JL1O300140.11616. 174448.KIEU THI HUYEN TRANG xin gui chut tam long nho"}, {"data": "2024-09-10", "mgd": "5242.67353", "amount": "200000", "nd": "MBVCB.6995270105.Minh Chau ho tro cuu tro sau bao Yagi.CT tu 1029956830 THAI THI MINH CHAU toi 0011001932418 MAT TRAN TO QUOC VN - BAN CUU TRO TW"}, {"data": "2024-09-10", "mgd": "5209.2353", "amount": "200000", "nd": "765614.100924.174501.mong gop chut tam long cho dong bao vung lu"}, {"data": "2024-09-10", "mgd": "5388.11694", "amount": "2000000", "nd": "020097040509101745102024GMFL037697.1169 4.174511.Vietcombank:0011001932418:Nguoi ham mo Nine Cao Khanh Tran tai Viet Nam ho tro dong bao anh huong boi bao Yagi"}, {"data": "2024-09-10", "mgd": "5241.67370", "amount": "500000", "nd": "MBVCB.6995270436.quyen gop ungho dong bao vung lu mien Bac.CT tu 0121000544450 BUI THI THU THUY toi 0011001932418 MAT TRAN TO QUOC VN - BAN CUU TRO TW"}, {"data": "2024-09-10", "mgd": "5209.2405", "amount": "200000", "nd": "766362.100924.174502.NGUYEN THI HONG HANG Chuyen tien"}]